harmony/__init__.py
harmony/harmony.py
harmony/utils.py
harmony/version.py
harmony_pytorch-0.1.8.dist-info/LICENSE
harmony_pytorch-0.1.8.dist-info/METADATA
harmony_pytorch-0.1.8.dist-info/WHEEL
harmony_pytorch-0.1.8.dist-info/top_level.txt
harmony_pytorch-0.1.8.dist-info/RECORD
