Metadata-Version: 2.1
Name: harmony-pytorch
Version: 0.1.8
Summary: Pytorch implementation of Harmony algorithm on single-cell sequencing data integration
Home-page: https://github.com/lilab-bcb/harmony-pytorch
Author: Yiming Yang, Bo Li
Author-email: yang.yihming@gmail.com, lijiganjun@gmail.com
Keywords: single-cell genomics data integration
Classifier: Development Status :: 3 - Alpha
Classifier: Intended Audience :: Developers
Classifier: Intended Audience :: Science/Research
Classifier: License :: OSI Approved :: BSD License
Classifier: Natural Language :: English
Classifier: Operating System :: MacOS
Classifier: Operating System :: Microsoft :: Windows :: Windows 10
Classifier: Operating System :: POSIX :: Linux
Classifier: Programming Language :: Python :: 3
Classifier: Programming Language :: Python :: 3 :: Only
Classifier: Topic :: Software Development :: Build Tools
Classifier: Topic :: Scientific/Engineering :: Bio-Informatics
Requires-Python: ~=3.8
License-File: LICENSE
Requires-Dist: torch >=1.12
Requires-Dist: numpy
Requires-Dist: pandas
Requires-Dist: psutil
Requires-Dist: threadpoolctl
Requires-Dist: scikit-learn >=0.23
